pubtools/sign/__init__.py
pubtools/sign/bundle.py
pubtools/sign/exceptions.py
pubtools/sign/utils.py
pubtools/sign/ansible/__init__.py
pubtools/sign/ansible/msg_clear_sign.py
pubtools/sign/clients/__init__.py
pubtools/sign/clients/msg.py
pubtools/sign/clients/msg_recv_client.py
pubtools/sign/clients/msg_send_client.py
pubtools/sign/clients/registry.py
pubtools/sign/conf/conf.py
pubtools/sign/models/__init__.py
pubtools/sign/models/msg.py
pubtools/sign/operations/__init__.py
pubtools/sign/operations/base.py
pubtools/sign/operations/blobsign.py
pubtools/sign/operations/clearsign.py
pubtools/sign/operations/containersign.py
pubtools/sign/results/__init__.py
pubtools/sign/results/blobsign.py
pubtools/sign/results/clearsign.py
pubtools/sign/results/containersign.py
pubtools/sign/results/operation_result.py
pubtools/sign/results/signing_results.py
pubtools/sign/signers/__init__.py
pubtools/sign/signers/cosignsigner.py
pubtools/sign/signers/msgsigner.py
pubtools_sign-1.0.6.dist-info/METADATA
pubtools_sign-1.0.6.dist-info/WHEEL
pubtools_sign-1.0.6.dist-info/entry_points.txt
pubtools_sign-1.0.6.dist-info/licenses/LICENSE
pubtools_sign-1.0.6.dist-info/RECORD
