Metadata-Version: 2.4
Name: pubtools-sign
Version: 1.0.6
Summary: Collection of tools producing signed artifacts
Author-email: Jindrich Luza <jluza@redhat.com>
License-File: LICENSE
Classifier: Development Status :: 5 - Production/Stable
Classifier: Intended Audience :: Developers
Classifier: License :: OSI Approved :: MIT License
Classifier: Programming Language :: Python :: 3
Classifier: Programming Language :: Python :: 3 :: Only
Classifier: Programming Language :: Python :: 3.7
Classifier: Programming Language :: Python :: 3.8
Classifier: Programming Language :: Python :: 3.9
Classifier: Programming Language :: Python :: 3.10
Classifier: Programming Language :: Python :: 3.11
Classifier: Topic :: Software Development :: Build Tools
Requires-Python: >=3.7
Requires-Dist: ansible-core
Requires-Dist: click
Requires-Dist: marshmallow
Requires-Dist: monotonic
Requires-Dist: opentelemetry-api
Requires-Dist: opentelemetry-exporter-otlp
Requires-Dist: opentelemetry-sdk
Requires-Dist: piny
Requires-Dist: pubtools>=1.4.0
Requires-Dist: pyopenssl
Requires-Dist: python-qpid-proton
Requires-Dist: requests
Requires-Dist: typing-extensions
Provides-Extra: dev
Requires-Dist: pytest; extra == 'dev'
Requires-Dist: tox; extra == 'dev'
